Workbook

Sheet Start Here
A1: The Busy Café Paradox: Excel Model
A2: Pour Decision Café is fictional. All figures are illustrative, not real café data.
A4: THE STORY
A5: Over 13 weeks, orders rose about 14% while average daily profit fell about 28%. Why?
A7: HOW TO PLAY
A8: 1. Go to the Simulator tab.
A9: 2. Pick a scenario from the dropdown (cell B4), or choose Custom and edit the yellow cells in column C.
A10: 3. Read the Scoreboard and the Advisor line. Everything recalculates instantly.
A11: 4. Open Weekly_Trend to see the 13-week history, and Raw_Data for the daily records.
A13: TABS
A14: Simulator: levers, baseline vs current, plain-English advisor, step-by-step workings.
A15: Weekly_Trend: weekly averages (formulas on Raw_Data) with a chart.
... A24: The Advisor line is a formula that reads the results. No AI model is connected inside this workbook.

Sheet Simulator
A1: Pour Decision Café: Simulator
A2: Illustrative figures only, not real café data. Edit yellow cells.
A4: Scenario | B4: Custom | C4: Custom uses column C. Other choices use the settings on the Assumptions tab.
A6: Lever | B6: Baseline | C6: Your setting (Custom) | D6: Active setting | E6: Allowed range
A7: Menu price ($) | B7: 6 | C7: 6 | D7: =MAX(4,MIN(9,IF($B$4="Custom",C7,INDEX(Assumptions!$B$15:$D$15,MATCH($B$4,Assumptions!$B$14:$D$14,0))))) -> 6 | E7: 4 to 9
A8: Staff hours per day | B8: 52 | C8: 52 | D8: =MAX(24,MIN(100,IF($B$4="Custom",C8,INDEX(Assumptions!$B$16:$D$16,MATCH($B$4,Assumptions!$B$14:$D$14,0))))) -> 52 | E8: 24 to 100
A9: Food thrown away (%) | B9: 0.14 | C9: 0.14 | D9: =MAX(0.02,MIN(0.3,IF($B$4="Custom",C9,INDEX(Assumptions!$B$17:$D$17,MATCH($B$4,Assumptions!$B$14:$D$14,0))))) -> 0.14 | E9: 0.02 to 0.3
A10: Longest line allowed (min) | B10: 15 | C10: 15 | D10: =MAX(3,MIN(15,IF($B$4="Custom",C10,INDEX(Assumptions!$B$18:$D$18,MATCH($B$4,Assumptions!$B$14:$D$14,0))))) -> 15 | E10: 3 to 15
A12: Scoreboard | B12: Baseline | C12: Now | D12: Change | E12: Better when
A13: Daily revenue ($) | B13: =B43 -> 2802 | C13: =C43 -> 2802 | D13: =C13-B13 -> 0 | E13: Higher
A14: Operating profit ($) | B14: =B48 -> 186.25395 | C14: =C48 -> 186.25395 | D14: =C14-B14 -> 0 | E14: Higher
A15: Guest happiness (0-100) | B15: =B40 -> 78.493891 | C15: =C40 -> 78.493891 | D15: =C15-B15 -> 0 | E15: Higher
A16: Orders per day | B16: =B42 -> 467 | C16: =C42 -> 467 | D16: =C16-B16 -> 0 | E16: Higher
A17: Food waste cost ($) | B17: =B46 -> 117.83605 | C17: =C46 -> 117.83605 | D17: =C17-B17 -> 0 | E17: Lower
A18: Average wait (min) | B18: =B37 -> 7.1687031 | C18: =C37 -> 7.1687031 | D18: =C18-B18 -> 0 | E18: Lower
A20: Advisor (formula-based, not AI)
A21: ="Orders are "&IF(D16>=0,"up ","down ")&TEXT(ABS(D16)/B16,"0%")&" and profit is "&IF(D14>=0,"up ","down ")&TEXT(ABS(D14),"$#,##0")&" a day vs baseline ("&TEXT(C14,"$#,##0;-$#,##0")&"). Happiness: "&TEXT(C15,"0")&"/100. "&IF(AND(D16>0,D14<-10),"Busier but poorer: the extra volume costs more to serve than it earns.",IF(AND(D14>10,D15<-3),"Profit rose, but at the expense of guest happiness.",IF(AND(D14<-10,D15>3),"Happier guests, but profit is thinner.",IF(D14>10,"A win for profit"&IF(D15>=1," and guests.","."),IF(AND(D16=0,D14=0),"This is the baseline. Try a scenario or change a yellow cell.","Little change versus baseline.")))))&IF(C38>0," Your line limit turns guests away.","")&IF(C39>0," Low waste means you run out of items.","")&IF(C14<0," At these settings the café loses money.","") -> Orders are up 0% and profit is up $0 a day vs baseline ($186). Happiness: 78/100. This is the baseline. Try a scenario or change a yellow cell.
A27: Workings (same formulas for baseline and current)
A28: Step | B28: Baseline | C28: Current | D28: How it works
A29: Menu price ($) | B29: =B7 -> 6 | C29: =D7 -> 6
A30: Staff hours | B30: =B8 -> 52 | C30: =D8 -> 52
A31: Waste share | B31: =B9 -> 0.14 | C31: =D9 -> 0.14
A32: Line limit (min) | B32: =B10 -> 15 | C32: =D10 -> 15
A33: Capacity (orders/day) | B33: =B30*Assumptions!$B$7 -> 520 | C33: =C30*Assumptions!$B$7 -> 520 | D33: Staff hours x orders per staff hour
A34: Demand at this price | B34: =Assumptions!$B$4*(Assumptions!$B$5/B29)^Assumptions!$B$6 -> 470 | C34: =Assumptions!$B$4*(Assumptions!$B$5/C29)^Assumptions!$B$6 -> 470 | D34: Higher price, fewer guests
A35: Demand vs capacity | B35: =MIN(1.6,B34/B33) -> 0.90384615 | C35: =MIN(1.6,C34/C33) -> 0.90384615
A36: Natural wait (min) | B36: =MIN(25,2+7*B35^3) -> 7.1687031 | C36: =MIN(25,2+7*C35^3) -> 7.1687031 | D36: Grows fast as demand nears capacity
A37: Actual wait (min) | B37: =MIN(B36,B32) -> 7.1687031 | C37: =MIN(C36,C32) -> 7.1687031 | D37: Line limit caps the wait
A38: Guests lost to line limit | B38: =IF(B36>B32,MIN(0.5,(B36-B32)/B36),0) -> 0 | C38: =IF(C36>C32,MIN(0.5,(C36-C32)/C36),0) -> 0 | D38: Share turned away if wait exceeds limit
A39: Lost to stock-outs | B39: =MAX(0,0.1-B31) -> 0 | C39: =MAX(0,0.1-C31) -> 0 | D39: Waste below 10% means running out
A40: Guest happiness | B40: =MAX(20,MIN(98,88-3*MAX(0,B37-4)-4*(B29-Assumptions!$B$5)-50*B39+0.06*(B30-52))) -> 78.493891 | C40: =MAX(20,MIN(98,88-3*MAX(0,C37-4)-4*(C29-Assumptions!$B$5)-50*C39+0.06*(C30-52))) -> 78.493891 | D40: 88 minus wait, price and stock-out penalties
A41: Repeat-visit multiplier | B41: =MAX(0.85,MIN(1.1,1+0.004*(B40-80))) -> 0.99397556 | C41: =MAX(0.85,MIN(1.1,1+0.004*(C40-80))) -> 0.99397556
A42: Orders served | B42: =MAX(0,ROUND(MIN(B34*B41,B33*1.05)*(1-B38)*(1-1.2*B39),0)) -> 467 | C42: =MAX(0,ROUND(MIN(C34*C41,C33*1.05)*(1-C38)*(1-1.2*C39),0)) -> 467 | D42: Demand x repeat multiplier, capped by staff, less lost guests
A43: Revenue ($) | B43: =B42*B29 -> 2802 | C43: =C42*C29 -> 2802
A44: Wages ($) | B44: =B30*Assumptions!$B$8 -> 1040 | C44: =C30*Assumptions!$B$8 -> 1040
A45: Food used ($) | B45: =B42*Assumptions!$B$9 -> 723.85 | C45: =C42*Assumptions!$B$9 -> 723.85
A46: Food wasted ($) | B46: =B45/(1-B31)-B45 -> 117.83605 | C46: =C45/(1-C31)-C45 -> 117.83605
A47: Fees + rent ($) | B47: =Assumptions!$B$11+B43*Assumptions!$B$10 -> 734.06 | C47: =Assumptions!$B$11+C43*Assumptions!$B$10 -> 734.06
A48: Operating profit ($) | B48: =B43-B44-B45-B46-B47 -> 186.25395 | C48: =C43-C44-C45-C46-C47 -> 186.25395
A49: Profit per order ($) | B49: =IF(B42=0,0,B48/B42) -> 0.39883074 | C49: =IF(C42=0,0,C48/C42) -> 0.39883074

Sheet Assumptions
A1: Assumptions & scenario settings
A2: Blue = editable input. Fictional, for teaching.
A3: Assumption | B3: Value | C3: Note
A4: Baseline demand (orders/day at reference price) | B4: 470 | C4: Fictional
A5: Reference price ($) | B5: 6 | C5: Fictional
A6: Price elasticity | B6: 1.2 | C6: Demand = D x (ref price / price)^elasticity
A7: Orders per staff hour | B7: 10 | C7: Capacity = hours x this
A8: Hourly wage, fully loaded ($) | B8: 20 | C8: Fictional
A9: Food cost per order served ($) | B9: 1.55 | C9: Fictional
A10: Card fees (% of revenue) | B10: 0.03 | C10: Fictional
A11: Rent & utilities per day ($) | B11: 650 | C11: Fictional
A13: Scenario settings
A14: Setting | B14: Grow Sales | C14: Protect Profit | D14: Delight Customers
A15: Menu price ($) | B15: 5.25 | C15: 6.75 | D15: 6
A16: Staff hours per day | B16: 64 | C16: 46 | D16: 70
A17: Food thrown away (%) | B17: 0.14 | C17: 0.08 | D17: 0.12
A18: Longest line allowed (min) | B18: 15 | C18: 10 | D18: 8

Sheet Raw_Data
A1: Date | B1: Orders | C1: Avg price ($) | D1: Staff hours | E1: Food waste (%) | F1: Avg wait (min) | G1: Happiness (0-100) | H1: Revenue ($) | I1: Wages ($) | J1: Food purchased ($) | K1: Food wasted ($) | L1: Card fees ($) | M1: Operating profit ($)
A2: 46204 | B2: 403 | C2: 6.34 | D2: 44 | E2: 0.086 | F2: 4.2 | G2: 87 | H2: =B2*C2 -> 2555.02 | I2: =D2*Assumptions!$B$8 -> 880 | J2: =B2*Assumptions!$B$9/(1-E2) -> 683.42451 | K2: =J2-B2*Assumptions!$B$9 -> 58.774508 | L2: =H2*Assumptions!$B$10 -> 76.6506 | M2: =H2-I2-J2-L2-Assumptions!$B$11 -> 264.94489
A3: 46205 | B3: 410 | C3: 6.35 | D3: 44 | E3: 0.083 | F3: 3.8 | G3: 86 | H3: =B3*C3 -> 2603.5 | I3: =D3*Assumptions!$B$8 -> 880 | J3: =B3*Assumptions!$B$9/(1-E3) -> 693.02072 | K3: =J3-B3*Assumptions!$B$9 -> 57.52072 | L3: =H3*Assumptions!$B$10 -> 78.105 | M3: =H3-I3-J3-L3-Assumptions!$B$11 -> 302.37428
A4: 46206 | B4: 390 | C4: 6.35 | D4: 44 | E4: 0.092 | F4: 3.9 | G4: 86 | H4: =B4*C4 -> 2476.5 | I4: =D4*Assumptions!$B$8 -> 880 | J4: =B4*Assumptions!$B$9/(1-E4) -> 665.7489 | K4: =J4-B4*Assumptions!$B$9 -> 61.248899 | L4: =H4*Assumptions!$B$10 -> 74.295 | M4: =H4-I4-J4-L4-Assumptions!$B$11 -> 206.4561
A5: 46207 | B5: 435 | C5: 6.33 | D5: 49 | E5: 0.095 | F5: 4.8 | G5: 85 | H5: =B5*C5 -> 2753.55 | I5: =D5*Assumptions!$B$8 -> 980 | J5: =B5*Assumptions!$B$9/(1-E5) -> 745.02762 | K5: =J5-B5*Assumptions!$B$9 -> 70.777624 | L5: =H5*Assumptions!$B$10 -> 82.6065 | M5: =H5-I5-J5-L5-Assumptions!$B$11 -> 295.91588
A6: 46208 | B6: 439 | C6: 6.36 | D6: 48 | E6: 0.086 | F6: 5.2 | G6: 86 | H6: =B6*C6 -> 2792.04 | I6: =D6*Assumptions!$B$8 -> 960 | J6: =B6*Assumptions!$B$9/(1-E6) -> 744.47484 | K6: =J6-B6*Assumptions!$B$9 -> 64.024836 | L6: =H6*Assumptions!$B$10 -> 83.7612 | M6: =H6-I6-J6-L6-Assumptions!$B$11 -> 353.80396
A7: 46209 | B7: 411 | C7: 6.41 | D7: 45 | E7: 0.1 | F7: 4.1 | G7: 86 | H7: =B7*C7 -> 2634.51 | I7: =D7*Assumptions!$B$8 -> 900 | J7: =B7*Assumptions!$B$9/(1-E7) -> 707.83333 | K7: =J7-B7*Assumptions!$B$9 -> 70.783333 | L7: =H7*Assumptions!$B$10 -> 79.0353 | M7: =H7-I7-J7-L7-Assumptions!$B$11 -> 297.64137
A8: 46210 | B8: 413 | C8: 6.39 | D8: 45 | E8: 0.095 | F8: 4.4 | G8: 84 | H8: =B8*C8 -> 2639.07 | I8: =D8*Assumptions!$B$8 -> 900 | J8: =B8*Assumptions!$B$9/(1-E8) -> 707.34807 | K8: =J8-B8*Assumptions!$B$9 -> 67.198066 | L8: =H8*Assumptions!$B$10 -> 79.1721 | M8: =H8-I8-J8-L8-Assumptions!$B$11 -> 302.54983
A9: 46211 | B9: 399 | C9: 6.34 | D9: 44 | E9: 0.09 | F9: 4 | G9: 85 | H9: =B9*C9 -> 2529.66 | I9: =D9*Assumptions!$B$8 -> 880 | J9: =B9*Assumptions!$B$9/(1-E9) -> 679.61538 | K9: =J9-B9*Assumptions!$B$9 -> 61.165385 | L9: =H9*Assumptions!$B$10 -> 75.8898 | M9: =H9-I9-J9-L9-Assumptions!$B$11 -> 244.15482
A10: 46212 | B10: 409 | C10: 6.35 | D10: 44 | E10: 0.09 | F10: 4.1 | G10: 87 | H10: =B10*C10 -> 2597.15 | I10: =D10*Assumptions!$B$8 -> 880 | J10: =B10*Assumptions!$B$9/(1-E10) -> 696.64835 | K10: =J10-B10*Assumptions!$B$9 -> 62.698352 | L10: =H10*Assumptions!$B$10 -> 77.9145 | M10: =H10-I10-J10-L10-Assumptions!$B$11 -> 292.58715
A11: 46213 | B11: 411 | C11: 6.37 | D11: 44 | E11: 0.099 | F11: 4.1 | G11: 85 | H11: =B11*C11 -> 2618.07 | I11: =D11*Assumptions!$B$8 -> 880 | J11: =B11*Assumptions!$B$9/(1-E11) -> 707.04772 | K11: =J11-B11*Assumptions!$B$9 -> 69.997725 | L11: =H11*Assumptions!$B$10 -> 78.5421 | M11: =H11-I11-J11-L11-Assumptions!$B$11 -> 302.48018
A12: 46214 | B12: 445 | C12: 6.37 | D12: 49 | E12: 0.099 | F12: 5.5 | G12: 86 | H12: =B12*C12 -> 2834.65 | I12: =D12*Assumptions!$B$8 -> 980 | J12: =B12*Assumptions!$B$9/(1-E12) -> 765.53829 | K12: =J12-B12*Assumptions!$B$9 -> 75.788291 | L12: =H12*Assumptions!$B$10 -> 85.0395 | M12: =H12-I12-J12-L12-Assumptions!$B$11 -> 354.07221
A13: 46215 | B13: 427 | C13: 6.29 | D13: 49 | E13: 0.092 | F13: 5 | G13: 86 | H13: =B13*C13 -> 2685.83 | I13: =D13*Assumptions!$B$8 -> 980 | J13: =B13*Assumptions!$B$9/(1-E13) -> 728.90969 | K13: =J13-B13*Assumptions!$B$9 -> 67.059692 | L13: =H13*Assumptions!$B$10 -> 80.5749 | M13: =H13-I13-J13-L13-Assumptions!$B$11 -> 246.34541
... A92: 46294 | B92: 478 | C92: 6.06 | D92: 51 | E92: 0.132 | F92: 7.3 | G92: 79 | H92: =B92*C92 -> 2896.68 | I92: =D92*Assumptions!$B$8 -> 1020 | J92: =B92*Assumptions!$B$9/(1-E92) -> 853.57143 | K92: =J92-B92*Assumptions!$B$9 -> 112.67143 | L92: =H92*Assumptions!$B$10 -> 86.9004 | M92: =H92-I92-J92-L92-Assumptions!$B$11 -> 286.20817

Sheet Weekly_Trend
A1: 13-week trend (daily averages per week)
A2: Formulas on Raw_Data. Illustrative data.
A4: Week starting | B4: Orders/day | C4: Profit/day ($) | D4: Happiness | E4: Avg wait (min) | F4: Waste cost/day ($)
A5: =Raw_Data!A2 -> 46204 | B5: =AVERAGEIFS(Raw_Data!$B$2:$B$92,Raw_Data!$A$2:$A$92,">="&A5,Raw_Data!$A$2:$A$92,"<"&A5+7) -> 414.42857 | C5: =AVERAGEIFS(Raw_Data!$M$2:$M$92,Raw_Data!$A$2:$A$92,">="&A5,Raw_Data!$A$2:$A$92,"<"&A5+7) -> 289.09804 | D5: =AVERAGEIFS(Raw_Data!$G$2:$G$92,Raw_Data!$A$2:$A$92,">="&A5,Raw_Data!$A$2:$A$92,"<"&A5+7) -> 85.714286 | E5: =AVERAGEIFS(Raw_Data!$F$2:$F$92,Raw_Data!$A$2:$A$92,">="&A5,Raw_Data!$A$2:$A$92,"<"&A5+7) -> 4.3428571 | F5: =AVERAGEIFS(Raw_Data!$K$2:$K$92,Raw_Data!$A$2:$A$92,">="&A5,Raw_Data!$A$2:$A$92,"<"&A5+7) -> 64.332569
A6: =A5+7 -> 46211 | B6: =AVERAGEIFS(Raw_Data!$B$2:$B$92,Raw_Data!$A$2:$A$92,">="&A6,Raw_Data!$A$2:$A$92,"<"&A6+7) -> 416.14286 | C6: =AVERAGEIFS(Raw_Data!$M$2:$M$92,Raw_Data!$A$2:$A$92,">="&A6,Raw_Data!$A$2:$A$92,"<"&A6+7) -> 281.22717 | D6: =AVERAGEIFS(Raw_Data!$G$2:$G$92,Raw_Data!$A$2:$A$92,">="&A6,Raw_Data!$A$2:$A$92,"<"&A6+7) -> 85.714286 | E6: =AVERAGEIFS(Raw_Data!$F$2:$F$92,Raw_Data!$A$2:$A$92,">="&A6,Raw_Data!$A$2:$A$92,"<"&A6+7) -> 4.5857143 | F6: =AVERAGEIFS(Raw_Data!$K$2:$K$92,Raw_Data!$A$2:$A$92,">="&A6,Raw_Data!$A$2:$A$92,"<"&A6+7) -> 66.989855
A7: =A6+7 -> 46218 | B7: =AVERAGEIFS(Raw_Data!$B$2:$B$92,Raw_Data!$A$2:$A$92,">="&A7,Raw_Data!$A$2:$A$92,"<"&A7+7) -> 423.14286 | C7: =AVERAGEIFS(Raw_Data!$M$2:$M$92,Raw_Data!$A$2:$A$92,">="&A7,Raw_Data!$A$2:$A$92,"<"&A7+7) -> 284.89987 | D7: =AVERAGEIFS(Raw_Data!$G$2:$G$92,Raw_Data!$A$2:$A$92,">="&A7,Raw_Data!$A$2:$A$92,"<"&A7+7) -> 83.714286 | E7: =AVERAGEIFS(Raw_Data!$F$2:$F$92,Raw_Data!$A$2:$A$92,">="&A7,Raw_Data!$A$2:$A$92,"<"&A7+7) -> 4.6428571 | F7: =AVERAGEIFS(Raw_Data!$K$2:$K$92,Raw_Data!$A$2:$A$92,">="&A7,Raw_Data!$A$2:$A$92,"<"&A7+7) -> 73.25309
A8: =A7+7 -> 46225 | B8: =AVERAGEIFS(Raw_Data!$B$2:$B$92,Raw_Data!$A$2:$A$92,">="&A8,Raw_Data!$A$2:$A$92,"<"&A8+7) -> 426.14286 | C8: =AVERAGEIFS(Raw_Data!$M$2:$M$92,Raw_Data!$A$2:$A$92,">="&A8,Raw_Data!$A$2:$A$92,"<"&A8+7) -> 275.79883 | D8: =AVERAGEIFS(Raw_Data!$G$2:$G$92,Raw_Data!$A$2:$A$92,">="&A8,Raw_Data!$A$2:$A$92,"<"&A8+7) -> 83.857143 | E8: =AVERAGEIFS(Raw_Data!$F$2:$F$92,Raw_Data!$A$2:$A$92,">="&A8,Raw_Data!$A$2:$A$92,"<"&A8+7) -> 4.9142857 | F8: =AVERAGEIFS(Raw_Data!$K$2:$K$92,Raw_Data!$A$2:$A$92,">="&A8,Raw_Data!$A$2:$A$92,"<"&A8+7) -> 75.998912
A9: =A8+7 -> 46232 | B9: =AVERAGEIFS(Raw_Data!$B$2:$B$92,Raw_Data!$A$2:$A$92,">="&A9,Raw_Data!$A$2:$A$92,"<"&A9+7) -> 434.28571 | C9: =AVERAGEIFS(Raw_Data!$M$2:$M$92,Raw_Data!$A$2:$A$92,">="&A9,Raw_Data!$A$2:$A$92,"<"&A9+7) -> 268.65461 | D9: =AVERAGEIFS(Raw_Data!$G$2:$G$92,Raw_Data!$A$2:$A$92,">="&A9,Raw_Data!$A$2:$A$92,"<"&A9+7) -> 83 | E9: =AVERAGEIFS(Raw_Data!$F$2:$F$92,Raw_Data!$A$2:$A$92,">="&A9,Raw_Data!$A$2:$A$92,"<"&A9+7) -> 5.4428571 | F9: =AVERAGEIFS(Raw_Data!$K$2:$K$92,Raw_Data!$A$2:$A$92,">="&A9,Raw_Data!$A$2:$A$92,"<"&A9+7) -> 80.727308
A10: =A9+7 -> 46239 | B10: =AVERAGEIFS(Raw_Data!$B$2:$B$92,Raw_Data!$A$2:$A$92,">="&A10,Raw_Data!$A$2:$A$92,"<"&A10+7) -> 433 | C10: =AVERAGEIFS(Raw_Data!$M$2:$M$92,Raw_Data!$A$2:$A$92,">="&A10,Raw_Data!$A$2:$A$92,"<"&A10+7) -> 251.10115 | D10: =AVERAGEIFS(Raw_Data!$G$2:$G$92,Raw_Data!$A$2:$A$92,">="&A10,Raw_Data!$A$2:$A$92,"<"&A10+7) -> 83.285714 | E10: =AVERAGEIFS(Raw_Data!$F$2:$F$92,Raw_Data!$A$2:$A$92,">="&A10,Raw_Data!$A$2:$A$92,"<"&A10+7) -> 5.7714286 | F10: =AVERAGEIFS(Raw_Data!$K$2:$K$92,Raw_Data!$A$2:$A$92,">="&A10,Raw_Data!$A$2:$A$92,"<"&A10+7) -> 82.941505
A11: =A10+7 -> 46246 | B11: =AVERAGEIFS(Raw_Data!$B$2:$B$92,Raw_Data!$A$2:$A$92,">="&A11,Raw_Data!$A$2:$A$92,"<"&A11+7) -> 440.85714 | C11: =AVERAGEIFS(Raw_Data!$M$2:$M$92,Raw_Data!$A$2:$A$92,">="&A11,Raw_Data!$A$2:$A$92,"<"&A11+7) -> 238.16446 | D11: =AVERAGEIFS(Raw_Data!$G$2:$G$92,Raw_Data!$A$2:$A$92,">="&A11,Raw_Data!$A$2:$A$92,"<"&A11+7) -> 81 | E11: =AVERAGEIFS(Raw_Data!$F$2:$F$92,Raw_Data!$A$2:$A$92,">="&A11,Raw_Data!$A$2:$A$92,"<"&A11+7) -> 5.9857143 | F11: =AVERAGEIFS(Raw_Data!$K$2:$K$92,Raw_Data!$A$2:$A$92,">="&A11,Raw_Data!$A$2:$A$92,"<"&A11+7) -> 93.941252
A12: =A11+7 -> 46253 | B12: =AVERAGEIFS(Raw_Data!$B$2:$B$92,Raw_Data!$A$2:$A$92,">="&A12,Raw_Data!$A$2:$A$92,"<"&A12+7) -> 446.57143 | C12: =AVERAGEIFS(Raw_Data!$M$2:$M$92,Raw_Data!$A$2:$A$92,">="&A12,Raw_Data!$A$2:$A$92,"<"&A12+7) -> 241.8486 | D12: =AVERAGEIFS(Raw_Data!$G$2:$G$92,Raw_Data!$A$2:$A$92,">="&A12,Raw_Data!$A$2:$A$92,"<"&A12+7) -> 81.714286 | E12: =AVERAGEIFS(Raw_Data!$F$2:$F$92,Raw_Data!$A$2:$A$92,">="&A12,Raw_Data!$A$2:$A$92,"<"&A12+7) -> 6.3 | F12: =AVERAGEIFS(Raw_Data!$K$2:$K$92,Raw_Data!$A$2:$A$92,">="&A12,Raw_Data!$A$2:$A$92,"<"&A12+7) -> 95.068072
A13: =A12+7 -> 46260 | B13: =AVERAGEIFS(Raw_Data!$B$2:$B$92,Raw_Data!$A$2:$A$92,">="&A13,Raw_Data!$A$2:$A$92,"<"&A13+7) -> 453.42857 | C13: =AVERAGEIFS(Raw_Data!$M$2:$M$92,Raw_Data!$A$2:$A$92,">="&A13,Raw_Data!$A$2:$A$92,"<"&A13+7) -> 237.29937 | D13: =AVERAGEIFS(Raw_Data!$G$2:$G$92,Raw_Data!$A$2:$A$92,">="&A13,Raw_Data!$A$2:$A$92,"<"&A13+7) -> 80.428571 | E13: =AVERAGEIFS(Raw_Data!$F$2:$F$92,Raw_Data!$A$2:$A$92,">="&A13,Raw_Data!$A$2:$A$92,"<"&A13+7) -> 6.6142857 | F13: =AVERAGEIFS(Raw_Data!$K$2:$K$92,Raw_Data!$A$2:$A$92,">="&A13,Raw_Data!$A$2:$A$92,"<"&A13+7) -> 98.408232
A14: =A13+7 -> 46267 | B14: =AVERAGEIFS(Raw_Data!$B$2:$B$92,Raw_Data!$A$2:$A$92,">="&A14,Raw_Data!$A$2:$A$92,"<"&A14+7) -> 457.85714 | C14: =AVERAGEIFS(Raw_Data!$M$2:$M$92,Raw_Data!$A$2:$A$92,">="&A14,Raw_Data!$A$2:$A$92,"<"&A14+7) -> 228.4225 | D14: =AVERAGEIFS(Raw_Data!$G$2:$G$92,Raw_Data!$A$2:$A$92,">="&A14,Raw_Data!$A$2:$A$92,"<"&A14+7) -> 79.714286 | E14: =AVERAGEIFS(Raw_Data!$F$2:$F$92,Raw_Data!$A$2:$A$92,">="&A14,Raw_Data!$A$2:$A$92,"<"&A14+7) -> 6.7714286 | F14: =AVERAGEIFS(Raw_Data!$K$2:$K$92,Raw_Data!$A$2:$A$92,">="&A14,Raw_Data!$A$2:$A$92,"<"&A14+7) -> 102.18029
A15: =A14+7 -> 46274 | B15: =AVERAGEIFS(Raw_Data!$B$2:$B$92,Raw_Data!$A$2:$A$92,">="&A15,Raw_Data!$A$2:$A$92,"<"&A15+7) -> 466.42857 | C15: =AVERAGEIFS(Raw_Data!$M$2:$M$92,Raw_Data!$A$2:$A$92,">="&A15,Raw_Data!$A$2:$A$92,"<"&A15+7) -> 235.09147 | D15: =AVERAGEIFS(Raw_Data!$G$2:$G$92,Raw_Data!$A$2:$A$92,">="&A15,Raw_Data!$A$2:$A$92,"<"&A15+7) -> 79.857143 | E15: =AVERAGEIFS(Raw_Data!$F$2:$F$92,Raw_Data!$A$2:$A$92,">="&A15,Raw_Data!$A$2:$A$92,"<"&A15+7) -> 6.9428571 | F15: =AVERAGEIFS(Raw_Data!$K$2:$K$92,Raw_Data!$A$2:$A$92,">="&A15,Raw_Data!$A$2:$A$92,"<"&A15+7) -> 108.7949
A16: =A15+7 -> 46281 | B16: =AVERAGEIFS(Raw_Data!$B$2:$B$92,Raw_Data!$A$2:$A$92,">="&A16,Raw_Data!$A$2:$A$92,"<"&A16+7) -> 468 | C16: =AVERAGEIFS(Raw_Data!$M$2:$M$92,Raw_Data!$A$2:$A$92,">="&A16,Raw_Data!$A$2:$A$92,"<"&A16+7) -> 200.91644 | D16: =AVERAGEIFS(Raw_Data!$G$2:$G$92,Raw_Data!$A$2:$A$92,">="&A16,Raw_Data!$A$2:$A$92,"<"&A16+7) -> 79 | E16: =AVERAGEIFS(Raw_Data!$F$2:$F$92,Raw_Data!$A$2:$A$92,">="&A16,Raw_Data!$A$2:$A$92,"<"&A16+7) -> 7.3285714 | F16: =AVERAGEIFS(Raw_Data!$K$2:$K$92,Raw_Data!$A$2:$A$92,">="&A16,Raw_Data!$A$2:$A$92,"<"&A16+7) -> 112.74016
A17: =A16+7 -> 46288 | B17: =AVERAGEIFS(Raw_Data!$B$2:$B$92,Raw_Data!$A$2:$A$92,">="&A17,Raw_Data!$A$2:$A$92,"<"&A17+7) -> 472 | C17: =AVERAGEIFS(Raw_Data!$M$2:$M$92,Raw_Data!$A$2:$A$92,">="&A17,Raw_Data!$A$2:$A$92,"<"&A17+7) -> 208.31025 | D17: =AVERAGEIFS(Raw_Data!$G$2:$G$92,Raw_Data!$A$2:$A$92,">="&A17,Raw_Data!$A$2:$A$92,"<"&A17+7) -> 77.857143 | E17: =AVERAGEIFS(Raw_Data!$F$2:$F$92,Raw_Data!$A$2:$A$92,">="&A17,Raw_Data!$A$2:$A$92,"<"&A17+7) -> 7.7 | F17: =AVERAGEIFS(Raw_Data!$K$2:$K$92,Raw_Data!$A$2:$A$92,">="&A17,Raw_Data!$A$2:$A$92,"<"&A17+7) -> 117.19271
A19: Change, first to last week | B19: =IF(B5=0,0,B17/B5-1) -> 0.13891761 | C19: =IF(C5=0,0,C17/C5-1) -> -0.27944774 | D19: =IF(D5=0,0,D17/D5-1) -> -0.091666667 | E19: =IF(E5=0,0,E17/E5-1) -> 0.77302632 | F19: =IF(F5=0,0,F17/F5-1) -> 0.82166995
